bm4d/__init__.py
bm4d/bm4d_ctypes.py
bm4d/libbm4d.so
bm4d/libbm4d_mac.so
bm4d/libbm4d_mac_arm.so
bm4d/libbm4d_win.so
bm4d/param_matching_data.mat
bm4d/profiles.py
bm4d-4.2.4.dist-info/LICENSE
bm4d-4.2.4.dist-info/METADATA
bm4d-4.2.4.dist-info/WHEEL
bm4d-4.2.4.dist-info/top_level.txt
bm4d-4.2.4.dist-info/RECORD
